realtime3d/__init__.py
realtime3d-0.0.1.dist-info/METADATA
realtime3d-0.0.1.dist-info/WHEEL
realtime3d-0.0.1.dist-info/top_level.txt
realtime3d-0.0.1.dist-info/RECORD
