Metadata-Version: 2.1
Name: realtime3d
Version: 0.0.1
Summary: realtime3d
Home-page: https://github.com/schrodinger/
Author: Andy Martin
Author-email: andy.martin@schrodinger.com
License: UNKNOWN
Platform: UNKNOWN
